beetroot/__init__.py
beetroot/beetroot.py
beetroot/comp.py
beetroot/exception.py
beetroot/file.py
beetroot/hashl.py
beetroot/math.py
beetroot/mem.py
beetroot/metadata.py
beetroot/obf.py
beetroot/objtype.py
beetroot/pkl.py
beetroot/random.py
beetroot/static.py
beetroot/stopwatch.py
beetroot/text.py
beetroot/tts.py
beetroot/yt.py
Beetroot-1.1.7.4.dist-info/LICENSE
Beetroot-1.1.7.4.dist-info/METADATA
Beetroot-1.1.7.4.dist-info/WHEEL
Beetroot-1.1.7.4.dist-info/top_level.txt
Beetroot-1.1.7.4.dist-info/RECORD
