Metadata-Version: 2.1
Name: Beetroot
Version: 1.1.7.4
Summary: A General Purpose Utility package for Python 3
Home-page: https://github.com/CuboidRaptor/Python-Beetroot
Author: Cuboid_Raptor
Author-email: fanjas112358@gmail.com
License: GNU GPLv3
Platform: UNKNOWN
Requires-Python: >=3.6
License-File: LICENSE
Provides-Extra: all
Requires-Dist: pyttsx3 (>=2.90) ; extra == 'all'
Requires-Dist: pillow (>=8.4.0) ; extra == 'all'
Requires-Dist: pyautogui (>=0.9.53) ; extra == 'all'
Requires-Dist: psutil (>=5.8.0) ; extra == 'all'
Requires-Dist: youtube-search (>=2.1.0) ; extra == 'all'
Requires-Dist: youtube-dl (>=2021.6.6) ; extra == 'all'
Requires-Dist: upsidedown (>=0.4) ; extra == 'all'
Requires-Dist: zalgo-text (>=0.6) ; extra == 'all'
Requires-Dist: Cython (>=0.29.24) ; extra == 'all'
Requires-Dist: setuptools (>=58.3.0) ; extra == 'all'
Requires-Dist: nltk (>=3.6.5) ; extra == 'all'
Requires-Dist: keyboard (>=0.13.5) ; extra == 'all'
Requires-Dist: base65536 (>=0.1.1) ; extra == 'all'
Provides-Extra: cython
Requires-Dist: Cython (>=0.29.24) ; extra == 'cython'
Requires-Dist: setuptools (>=58.3.0) ; extra == 'cython'
Provides-Extra: img
Requires-Dist: pillow (>=8.4.0) ; extra == 'img'
Requires-Dist: pyautogui (>=0.9.53) ; extra == 'img'
Provides-Extra: keyboard
Requires-Dist: keyboard (>=0.13.5) ; extra == 'keyboard'
Provides-Extra: ram
Requires-Dist: psutil (>=5.8.0) ; extra == 'ram'
Provides-Extra: speed
Requires-Dist: Cython (>=0.29.24) ; extra == 'speed'
Provides-Extra: text
Requires-Dist: upsidedown (>=0.4) ; extra == 'text'
Requires-Dist: zalgo-text (>=0.6) ; extra == 'text'
Requires-Dist: nltk (>=3.6.5) ; extra == 'text'
Requires-Dist: base65536 (>=0.1.1) ; extra == 'text'
Provides-Extra: tts
Requires-Dist: pyttsx3 (>=2.90) ; extra == 'tts'
Provides-Extra: yt
Requires-Dist: youtube-search (>=2.1.0) ; extra == 'yt'
Requires-Dist: youtube-dl (>=2021.6.6) ; extra == 'yt'
